_hunspell.cp35-win_amd64.pyd
Hunspell_CFFI-1.1.2.data/data/libhunspell.dll
Hunspell_CFFI-1.1.2.dist-info/DESCRIPTION.rst
Hunspell_CFFI-1.1.2.dist-info/METADATA
Hunspell_CFFI-1.1.2.dist-info/RECORD
Hunspell_CFFI-1.1.2.dist-info/WHEEL
Hunspell_CFFI-1.1.2.dist-info/metadata.json
Hunspell_CFFI-1.1.2.dist-info/top_level.txt
hunspell_cffi/__init__.py
hunspell_cffi/build.py
