Metadata-Version: 2.0
Name: Hunspell-CFFI
Version: 1.1.2
Summary: A CFFI binding for the Hunspell spellcheck library
Home-page: https://github.com/Sentynel/hunspell-cffi
Author: Sam Lade
Author-email: hunspell-cffi@sentynel.com
License: MIT
Keywords: spelling,spellcheck
Platform: UNKNOWN
Classifier: Development Status :: 5 - Production/Stable
Classifier: Intended Audience :: Developers
Classifier: Operating System :: OS Independent
Classifier: License :: OSI Approved :: MIT License
Classifier: Programming Language :: Python :: 3 :: Only
Classifier: Programming Language :: Python :: 3.3
Classifier: Programming Language :: Python :: 3.4
Classifier: Programming Language :: Python :: 3.5
Requires-Dist: cffi (>=1.0.0)
